pyaxml/__init__.py
pyaxml/arscobject.py
pyaxml/arsctableconfig.py
pyaxml/arsctype.py
pyaxml/axml.py
pyaxml/cli.py
pyaxml/conf.py
pyaxml/header.py
pyaxml/public.json
pyaxml/public.py
pyaxml/public.xml
pyaxml/stringblocks.py
pyaxml/xmlelement.py
pyaxml/proto/__init__.py
pyaxml/proto/axml.proto
pyaxml/proto/axml_pb2.py
pyaxml-0.0.34.dist-info/licenses/LICENSE
pyaxml-0.0.34.dist-info/METADATA
pyaxml-0.0.34.dist-info/WHEEL
pyaxml-0.0.34.dist-info/entry_points.txt
pyaxml-0.0.34.dist-info/top_level.txt
pyaxml-0.0.34.dist-info/RECORD
