Metadata-Version: 2.4
Name: pyaxml
Version: 0.0.34
Summary: Manipulate AXML file and create one from scratch
Author-email: "Benoit Forgette (MadSquirrel)" <benoit.forgette@ci-yow.com>
Maintainer-email: "Benoit Forgette (MadSquirrel)" <benoit.forgette@ci-yow.com>
License:                     GNU GENERAL PUBLIC LICENSE
Project-URL: Homepage, https://ci-yow.com
Project-URL: Documentation, https://pyaxml.ci-yow.com
Project-URL: Repository, https://gitlab.com/MadSquirrels/mobile/pyaxml
Classifier: Development Status :: 4 - Beta
Classifier: Programming Language :: Python
Requires-Python: >=3.8
License-File: LICENSE
Requires-Dist: click
Requires-Dist: protobuf
Requires-Dist: lxml
Dynamic: license-file
